multidst/__init__.py
multidst/functions.py
multidst/methods/BH.py
multidst/methods/BY.py
multidst/methods/__init__.py
multidst/methods/bonf.py
multidst/methods/holm_bonf.py
multidst/methods/qval.py
multidst/methods/sgof.py
multidst/utils/__init__.py
multidst/utils/common_indices.py
multidst/utils/visualization.py
multidst/utils/weighting.py
multidst-0.1.11.dist-info/licenses/LICENSE
multidst-0.1.11.dist-info/METADATA
multidst-0.1.11.dist-info/WHEEL
multidst-0.1.11.dist-info/top_level.txt
multidst-0.1.11.dist-info/RECORD
