Metadata-Version: 2.4
Name: MultiDST
Version: 0.1.11
Summary: A toolkit for multiple hypothesis testing that implements common FWER and FDR control procedures, with intuitive significance visualisation using the Significant Index Plot.
Author: R.A.S. Ouchithya
License: MIT
Requires-Python: >=3.10
License-File: LICENSE
Requires-Dist: numpy
Requires-Dist: pandas
Requires-Dist: scipy
Requires-Dist: statsmodels
Requires-Dist: matplotlib
Provides-Extra: dev
Requires-Dist: twine>4.0.2; extra == "dev"
Dynamic: author
Dynamic: description
Dynamic: description-content-type
Dynamic: license
Dynamic: license-file
Dynamic: provides-extra
Dynamic: requires-dist
Dynamic: requires-python
Dynamic: summary
